MANIFEST.in
setup.py
Amuru.egg-info/PKG-INFO
Amuru.egg-info/SOURCES.txt
Amuru.egg-info/dependency_links.txt
Amuru.egg-info/requires.txt
Amuru.egg-info/top_level.txt
Core/__init__.py
Core/command.py
Core/engine.py
Core/exceptions.py
Core/receiver.py
Core/receiver_log.py
Core/recording.py
Core/request.py
tests/__init__.py
tests/engine_tests.py
tests/engine_tests_data.py