Metadata-Version: 1.1
Name: Amuru
Version: 1.0.0
Summary: a tiny command invoker/dispatcher pattern library 
Home-page: https://github.com/thynquest/amuru.git
Author: Franck Kambiwa
Author-email: thynquest@gmail.com
License: MIT
Keywords: command invoker/dispatcher pattern library
Platform: UNKNOWN
Classifier: Development Status :: 2 - Pre-Alpha
Classifier: Programming Language :: Python
Classifier: Programming Language :: Python :: 3.6
Classifier: License :: OSI Approved :: MIT License
Classifier: Intended Audience :: Developers
Classifier: Natural Language :: English
Classifier: Operating System :: OS Independent
Classifier: Topic :: System :: Monitoring
Classifier: Topic :: System :: Distributed Computing
